Metadata-Version: 2.1
Name: flawunicode
Version: 0.1.3
Summary: detect flaw or encoding error in unicode text
Home-page: https://github.com/currentslab/flawunicode
Author: Ray
Author-email: ray@currentsapi.services
License: MIT License
Keywords: unicode,detection,annomaly
Classifier: Development Status :: 5 - Production/Stable
Classifier: Intended Audience :: Developers
Classifier: License :: OSI Approved :: MIT License
Classifier: Operating System :: OS Independent
Classifier: Programming Language :: Python :: 3
Classifier: Programming Language :: Python :: 3.4
Classifier: Programming Language :: Python :: 3.5
Classifier: Programming Language :: Python :: 3.6
Classifier: Programming Language :: Python :: 3.7
Classifier: Programming Language :: Python :: 3.8
Classifier: Programming Language :: Python :: 3.9
Classifier: Programming Language :: Python :: 3.10
Classifier: Programming Language :: Python :: 3.11
License-File: LICENSE
